venmo_api/__init__.py
venmo_api/venmo.py
venmo_api/apis/__init__.py
venmo_api/apis/auth_api.py
venmo_api/apis/payment_api.py
venmo_api/apis/user_api.py
venmo_api/models/__init__.py
venmo_api/models/base_model.py
venmo_api/models/comment.py
venmo_api/models/exception.py
venmo_api/models/json_schema.py
venmo_api/models/mention.py
venmo_api/models/page.py
venmo_api/models/payment.py
venmo_api/models/payment_method.py
venmo_api/models/transaction.py
venmo_api/models/user.py
venmo_api/utils/__init__.py
venmo_api/utils/api_client.py
venmo_api/utils/api_util.py
venmo_api/utils/model_util.py
venmo_api-0.3.1.dist-info/LICENSE
venmo_api-0.3.1.dist-info/METADATA
venmo_api-0.3.1.dist-info/WHEEL
venmo_api-0.3.1.dist-info/top_level.txt
venmo_api-0.3.1.dist-info/RECORD
